notification_service/__init__.py
notification_service/__main__.py
notification_service/alembic.ini
notification_service/base_notification.py
notification_service/client.py
notification_service/event_storage.py
notification_service/high_availability.py
notification_service/mongo_event_storage.py
notification_service/mongo_notification.py
notification_service/server.py
notification_service/server_config.py
notification_service/service.py
notification_service/settings.py
notification_service/version.py
notification_service/cli/__init__.py
notification_service/cli/cli_parser.py
notification_service/cli/simple_table.py
notification_service/cli/commands/__init__.py
notification_service/cli/commands/config_command.py
notification_service/cli/commands/db_command.py
notification_service/cli/commands/event_command.py
notification_service/cli/commands/server_command.py
notification_service/cli/commands/version_command.py
notification_service/config_templates/__init__.py
notification_service/config_templates/default_notification_server.yaml
notification_service/migrations/__init__.py
notification_service/migrations/env.py
notification_service/migrations/versions/29623a4151ed_add_member.py
notification_service/migrations/versions/87cb292bcc31_add_tables.py
notification_service/migrations/versions/__init__.py
notification_service/proto/__init__.py
notification_service/proto/notification_service_pb2.py
notification_service/proto/notification_service_pb2_grpc.py
notification_service/util/__init__.py
notification_service/util/cli.py
notification_service/util/config.py
notification_service/util/db.py
notification_service/util/utils.py
notification_service-0.3.1.data/scripts/init-notification-env.sh
notification_service-0.3.1.data/scripts/start-notification.sh
notification_service-0.3.1.data/scripts/start_notification_server.py
notification_service-0.3.1.data/scripts/stop-notification.sh
notification_service-0.3.1.dist-info/METADATA
notification_service-0.3.1.dist-info/WHEEL
notification_service-0.3.1.dist-info/entry_points.txt
notification_service-0.3.1.dist-info/top_level.txt
notification_service-0.3.1.dist-info/RECORD
