Metadata-Version: 2.1
Name: notification-service
Version: 0.3.1
Summary: A Python package which provides stable notification service.
Home-page: https://github.com/flink-extended/ai-flow
Author: UNKNOWN
Author-email: flink.aiflow@gmail.com
License: UNKNOWN
Platform: UNKNOWN
Requires-Dist: protobuf (==3.15.6)
Requires-Dist: grpcio (==1.35.0)
Requires-Dist: sqlalchemy (<2,>=1.3.18)
Requires-Dist: pyyaml (<5.4,>=5.1)
Requires-Dist: rich (==9.2.0)
Requires-Dist: python-dateutil (==2.8.0)
Requires-Dist: alembic (<2.0,>=1.2)
Requires-Dist: python-daemon (<2.2,>=2.1.1)
